{"ENTITY_ID":6,"tables":[{"id":"07a3ca99-b299-4975-aacc-041e0bd3ab4a","position":{"x":280,"y":62},"data":{"table_name":"Competitor","fields":[{"fieldName":"id","fieldType":3,"isPK":true,"isNotNull":false,"isUnique":false,"defaultValue":"","args":[1,1],"isAutoIncrement":true},{"fieldName":"competitor_name","fieldType":10,"isPK":false,"isNotNull":true,"isUnique":true,"defaultValue":"","args":"50","isAutoIncrement":false}],"next_id":2,"checkName":[],"checkCondition":[]}},{"id":"91c7af07-02e1-4f52-bc70-5e4435f3a516","position":{"x":100,"y":220},"data":{"table_name":"Contestant","fields":[],"next_id":1,"checkName":[],"checkCondition":[]}},{"id":"a8a9425e-fd7c-4ec1-8be0-e2350af8890c","position":{"x":682,"y":316},"data":{"table_name":"Creator","fields":[],"next_id":1,"checkName":[],"checkCondition":[]}},{"id":"92512245-dd6b-496d-b700-58d6145b2ca3","position":{"x":298,"y":763},"data":{"table_name":"Competition","fields":[{"fieldName":"id","fieldType":3,"isPK":true,"isNotNull":false,"isUnique":false,"defaultValue":"","args":[1,1],"isAutoIncrement":true},{"fieldName":"competition_name","fieldType":10,"isPK":false,"isNotNull":true,"isUnique":true,"defaultValue":"","args":"50","isAutoIncrement":false},{"fieldName":"start_date","fieldType":8,"isPK":false,"isNotNull":true,"isUnique":false,"defaultValue":"","args":"","isAutoIncrement":false},{"fieldName":"end_date","fieldType":8,"isPK":false,"isNotNull":true,"isUnique":false,"defaultValue":"","args":"","isAutoIncrement":false}],"next_id":4,"checkName":[],"checkCondition":[]}},{"id":"e0d79f6a-4586-4350-bdd9-fc6e26c67520","position":{"x":301,"y":491},"data":{"table_name":"Route","fields":[{"fieldName":"id","fieldType":3,"isPK":true,"isNotNull":false,"isUnique":false,"defaultValue":"","args":[1,1],"isAutoIncrement":true},{"fieldName":"base_file","fieldType":11,"isPK":false,"isNotNull":false,"isUnique":false,"defaultValue":"","args":"50","isAutoIncrement":false}],"next_id":3,"checkName":[],"checkCondition":[]}},{"id":"98ab9ac0-28cf-4794-bc4f-7a66652da298","position":{"x":180,"y":344},"data":{"table_name":"Submission","fields":[{"fieldName":"submission_file","fieldType":11,"isPK":false,"isNotNull":false,"isUnique":false,"defaultValue":"","args":["512"],"isAutoIncrement":false}],"next_id":1,"checkName":[],"checkCondition":[]}}],"links":[{"source":"91c7af07-02e1-4f52-bc70-5e4435f3a516","target":"07a3ca99-b299-4975-aacc-041e0bd3ab4a","order":"parenting","sourceCard":"0:1","targetCard":"0:1","label":"complete","hierType":"complete","sourceisweak":false,"targetisweak":false},{"source":"a8a9425e-fd7c-4ec1-8be0-e2350af8890c","target":"07a3ca99-b299-4975-aacc-041e0bd3ab4a","order":"parenting","sourceCard":"0:1","targetCard":"0:1","label":"complete","hierType":"complete","sourceisweak":false,"targetisweak":false},{"source":"92512245-dd6b-496d-b700-58d6145b2ca3","target":"e0d79f6a-4586-4350-bdd9-fc6e26c67520","order":"normal","sourceCard":"1:n","targetCard":"1:n","label":"","hierType":null,"sourceisweak":false,"targetisweak":false},{"source":"91c7af07-02e1-4f52-bc70-5e4435f3a516","target":"98ab9ac0-28cf-4794-bc4f-7a66652da298","order":"normal","sourceCard":"1:1","targetCard":"0:n","label":"","hierType":null,"sourceisweak":false,"targetisweak":true},{"source":"e0d79f6a-4586-4350-bdd9-fc6e26c67520","target":"98ab9ac0-28cf-4794-bc4f-7a66652da298","order":"normal","sourceCard":"1:1","targetCard":"0:n","label":"","hierType":null,"sourceisweak":false,"targetisweak":true},{"source":"a8a9425e-fd7c-4ec1-8be0-e2350af8890c","target":"e0d79f6a-4586-4350-bdd9-fc6e26c67520","order":"normal","sourceCard":"1:1","targetCard":"1:n","label":"","hierType":null,"sourceisweak":false,"targetisweak":false},{"source":"a8a9425e-fd7c-4ec1-8be0-e2350af8890c","target":"92512245-dd6b-496d-b700-58d6145b2ca3","order":"normal","sourceCard":"1:1","targetCard":"1:n","label":"","hierType":null,"sourceisweak":false,"targetisweak":false}],"normalization":1,"database":0}